<recipe>
  <title>4-Flavor Giant Sheet Pan Breakfast Sandwich Recipe by Tasty</title>
  <url>https://tasty.co/recipe/4-flavor-giant-sheet-pan-breakfast-sandwich</url>
  <type>single</type>
  <ingredients>
    <ingredient num="0">11061 9517 13278 2650 10968 13278 1626 5981 </ingredient>
    <ingredient num="1">11061 13278 2597 14463 8574 9917 </ingredient>
    <ingredient num="2">4061 9517 13278 5802 13278 5564 8007 </ingredient>
    <ingredient num="3">13086 9486 13278 4168 5766 </ingredient>
    <ingredient num="4">409 13278 2597 12708 </ingredient>
    <ingredient num="5">1580 2605 13278 5802 13278 2935 8007 </ingredient>
    <ingredient num="6">12610 560 11567 </ingredient>
    <ingredient num="7">10986 560 11567 </ingredient>
    <ingredient num="8">11061 8535 13278 4903 8932 </ingredient>
    <ingredient num="9">6209 2602 560 11567 </ingredient>
    <ingredient num="10">12200 7280 560 11567 </ingredient>
    <ingredient num="11">11061 13278 2192 7983 13280 6616 1010 </ingredient>
    <ingredient num="12">13086 8535 13278 9241 13810 10844 </ingredient>
    <ingredient num="13">4061 13278 629 6396 </ingredient>
    <ingredient num="14">4061 8535 13278 9784 14538 </ingredient>
    <ingredient num="15">11061 13278 13895 3745 </ingredient>
  </ingredients>
  <categories>
    <category num="0">American</category>
    <category num="1">Breakfast</category>
    <category num="2">Brunch</category>
    <category num="3">Casual Party</category>
  </categories>
  <video>
    <low>https://vid.tasty.co/output/111411/hls24_1538758413.m3u8</low>
    <high>https://vid.tasty.co/output/111411/landscape_720/1538758413</high>
  </video>
  <steps>
    <step num="0">3915 11951 10439 560 13194 13180 9207 13086 13375 12042 10765 8036 1391 3550 8831 </step>
    <step num="1">6823 11951 2650 12712 10950 5994 2597 14511 4120 11951 2650 3446 14463 9889 13817 4168 14158 283 560 4398 6770 148 11155 560 12319 </step>
    <step num="2">877 4428 8830 8580 371 11951 9864 10765 768 2988 3584 13817 10903 7990 8489 11004 1681 1762 14138 12753 13817 6728 4428 4150 2696 </step>
    <step num="3">6823 11951 6216 12712 10950 5994 2597 14511 4120 11951 14463 9889 12610 13817 12375 </step>
    <step num="4">1083 11951 6216 10968 1802 11951 374 9864 10765 8800 2988 3584 13817 10903 7990 8489 11004 1681 11951 5832 12573 2043 9892 </step>
    <step num="5">9207 6646 10765 213 1391 8580 8036 371 3550 8831 </step>
    <step num="6">6695 11951 4901 8932 8535 210 5994 11090 7811 11951 10707 371 11951 10765 213 13817 7454 13220 4255 143 </step>
    <step num="7">5570 11951 7983 13280 1010 210 5994 11090 1896 11951 4901 8932 13817 10707 1391 11951 5524 14538 10832 </step>
    <step num="8">12595 11951 551 8162 2532 371 11951 3550 12 11770 1681 1762 3313 11951 1010 560 3535 5994 12675 8830 11951 3061 5677 13817 11951 8597 7857 </step>
    <step num="9">5570 11951 8597 6396 4255 11951 551 2532 371 11951 10765 213 13817 10707 1391 11951 9784 4496 </step>
    <step num="10">10211 11951 10439 2281 560 9988 1390 13817 10903 11951 5677 7990 666 11004 1681 11951 3061 9490 545 7492 13817 11951 14538 7312 1311 </step>
    <step num="11">12474 5994 4669 8667 11826 11951 125 11695 1391 5994 2650 10869 6960 5569 11951 6216 14614 6695 11951 8932 13817 11649 5677 210 1033 4255 11951 13784 13494 11951 4901 8932 13817 13220 1391 12200 7280 5358 13 13494 1391 11951 437 2650 14614 </step>
    <step num="12">3235 669 8268 14348 13817 1966 419 5895 7558 210 3550 12 13817 13351 210 2237 2759 3801 7990 3386 560 3917 10941 13817 10503 4255 14070 7990 6285 2933 11004 1681 3557 9490 10316 </step>
    <step num="13">9092 </step>
  </steps>
  <steps_updated>
    <steps_updated num="0">3915 11951 10439 560 13194 13180 </steps_updated>
    <steps_updated num="1">9207 13086 13375 12042 10765 8036 1391 3550 8831 </steps_updated>
    <steps_updated num="2">6823 11951 2650 12712 10950 5994 2597 14511 4120 11951 2650 3446 14463 9889 13817 4168 14158 </steps_updated>
    <steps_updated num="3">283 560 4398 6770 148 11155 560 12319 </steps_updated>
    <steps_updated num="4">877 4428 8830 8580 371 11951 9864 10765 768 </steps_updated>
    <steps_updated num="5">2988 3584 13817 10903 7990 8489 11004 1681 1762 14138 12753 13817 6728 4428 4150 2696 </steps_updated>
    <steps_updated num="6">6823 11951 6216 12712 10950 5994 2597 14511 4120 11951 14463 9889 12610 13817 12375 </steps_updated>
    <steps_updated num="7">1083 11951 6216 10968 1802 11951 374 9864 10765 8800 </steps_updated>
    <steps_updated num="8">2988 3584 13817 10903 7990 8489 11004 1681 11951 5832 12573 2043 9892 </steps_updated>
    <steps_updated num="9">9207 6646 10765 213 1391 8580 8036 371 3550 8831 </steps_updated>
    <steps_updated num="10">6695 11951 4901 8932 8535 210 5994 11090 7811 11951 10707 371 11951 10765 213 13817 7454 13220 4255 143 </steps_updated>
    <steps_updated num="11">5570 11951 7983 13280 1010 210 5994 11090 1896 11951 4901 8932 13817 10707 1391 11951 5524 14538 10832 </steps_updated>
    <steps_updated num="12">12595 11951 551 8162 2532 371 11951 3550 12 11770 1681 1762 3313 11951 1010 560 3535 5994 12675 8830 11951 3061 5677 13817 11951 8597 7857 </steps_updated>
    <steps_updated num="13">5570 11951 8597 6396 4255 11951 551 2532 371 11951 10765 213 13817 10707 1391 11951 9784 4496 </steps_updated>
    <steps_updated num="14">10211 11951 10439 2281 560 9988 1390 13817 10903 11951 5677 7990 666 11004 1681 11951 3061 9490 545 7492 13817 11951 14538 7312 1311 </steps_updated>
    <steps_updated num="15">12474 5994 4669 8667 11826 11951 125 11695 1391 5994 2650 10869 6960 5569 11951 6216 14614 </steps_updated>
    <steps_updated num="16">6695 11951 8932 13817 11649 5677 210 1033 4255 11951 13784 </steps_updated>
    <steps_updated num="17">13494 11951 4901 8932 13817 13220 1391 12200 7280 5358 13 </steps_updated>
    <steps_updated num="18">13494 1391 11951 437 2650 14614 </steps_updated>
    <steps_updated num="19">3235 669 8268 14348 13817 1966 419 5895 7558 210 3550 12 13817 13351 210 2237 2759 3801 7990 3386 560 3917 10941 13817 10503 4255 14070 7990 6285 2933 11004 1681 3557 9490 10316 </steps_updated>
    <steps_updated num="20">9092 </steps_updated>
  </steps_updated>
</recipe>