<?xml version='1.0' encoding='UTF-8'?>
<recipe>
  <title>Healthy Slow Cooker Spinach Artichoke Dip Recipe by Tasty</title>
  <url>https://tasty.co/recipe/healthy-slow-cooker-spinach-artichoke-dip</url>
  <type>compilation</type>
  <comp_url>https://tasty.co/compilation/slow-cooker-dual-dips</comp_url>
  <ingredients>
    <ingredient num="0">8 oz ; reduced fat cream cheese ; (225 g) </ingredient>
    <ingredient num="1">¼ cup ; nonfat greek yogurt ; (70 g) </ingredient>
    <ingredient num="2">2 cups ; canned artichoke heart, drained and chopped ; (335 g) </ingredient>
    <ingredient num="3">2 cups ; frozen spinach ; (310 g) </ingredient>
    <ingredient num="4">1 cup ; low fat mozzarella cheese ; (100 g) </ingredient>
  </ingredients>
  <categories>
    <category num="0">American</category>
    <category num="1">Healthy</category>
    <category num="2">Low-Carb</category>
    <category num="3">Vegetarian</category>
    <category num="4">Appetizers</category>
    <category num="5">Sides</category>
    <category num="6">Game Day</category>
    <category num="7">Casual Party</category>
  </categories>
  <video>
    <low>https://vid.tasty.co/output/57253/low_1508451314.m3u8</low>
    <high>https://vid.tasty.co/output/57253/mp4_720x1280/1508451314</high>
  </video>
  <duration>
    <start_time>-1</start_time>
    <end_time>-1</end_time>
  </duration>
  <steps>
    <step num="0">Add all ingredients into a slow cooker and stir until combined </step>
    <step num="1">Cook on high for 4 hours, or until all cheese is melted </step>
    <step num="2">Enjoy! </step>
  </steps>
  <steps_updated>
    <steps_updated num="0">Add all ingredients into a slow cooker and stir until combined </steps_updated>
    <steps_updated num="1">Cook on high for 4 hours, or until all cheese is melted </steps_updated>
    <steps_updated num="2">Enjoy! </steps_updated>
  </steps_updated>
  <duration_human>
    <start_time>00488</start_time>
    <end_time>01236</end_time>
  </duration_human>
</recipe>