<recipe>
  <title>Confetti Crullers Recipe by Tasty</title>
  <url>https://tasty.co/recipe/confetti-crullers</url>
  <type>single</type>
  <ingredients>
    <ingredient num="0">3917 2605 13278 7974 10907 8580 11078 472 13278 2583 5981 </ingredient>
    <ingredient num="1">3917 12791 9517 13278 12282 13278 1513 8007 </ingredient>
    <ingredient num="2">3917 12791 9517 13278 5802 13278 1513 8007 </ingredient>
    <ingredient num="3">12791 2605 13278 8653 4834 13278 2264 5981 </ingredient>
    <ingredient num="4">3917 8071 13278 82 </ingredient>
    <ingredient num="5">3917 2605 13278 13521 890 13278 9373 5981 </ingredient>
    <ingredient num="6">1580 2605 13278 3305 2168 890 13278 9377 5981 </ingredient>
    <ingredient num="7">8580 2031 13278 10765 11703 </ingredient>
    <ingredient num="8">2933 13278 2597 12708 </ingredient>
    <ingredient num="9">8580 2031 13278 1319 9525 3247 </ingredient>
    <ingredient num="10">1813 2605 13278 1226 11815 7789 3954 7990 3297 13278 9377 5981 </ingredient>
    <ingredient num="11">6735 9517 13278 11338 5766 13278 10839 1767 </ingredient>
    <ingredient num="12">4061 9517 13278 6885 6145 9121 13278 4551 5981 </ingredient>
    <ingredient num="13">4061 9486 13278 5802 </ingredient>
    <ingredient num="14">3917 8071 13278 1319 10937 </ingredient>
    <ingredient num="15">13086 9486 13278 13033 13810 564 </ingredient>
    <ingredient num="16">2597 3508 14361 1803 </ingredient>
    <ingredient num="17">11358 7256 9270 </ingredient>
  </ingredients>
  <categories>
    <category num="0">French</category>
    <category num="1">Comfort Food</category>
    <category num="2">Vegetarian</category>
    <category num="3">Breakfast</category>
    <category num="4">Brunch</category>
    <category num="5">Kid-Friendly</category>
    <category num="6">Indulgent Sweets</category>
    <category num="7">Bakery Goods</category>
    <category num="8">Special Occasion</category>
  </categories>
  <video>
    <low>https://vid.tasty.co/output/103375/hls24_1532714820.m3u8</low>
    <high>https://vid.tasty.co/output/103375/landscape_720/1532714820</high>
  </video>
  <steps>
    <step num="0">10950 5994 2597 10083 11770 13757 14307 4120 11951 10907 13384 9889 6145 13817 12051 283 1681 11951 9924 9490 5335 13817 11951 2373 9490 11898 6285 2933 12689 </step>
    <step num="1">3783 8341 11951 13521 13817 3305 2168 1949 13817 11951 10765 11703 669 11951 6222 5802 10665 8697 10279 13328 5465 7990 2933 3954 12689 6054 11951 10083 6781 7855 13817 6142 1391 5994 7700 560 10694 11951 9453 </step>
    <step num="2">11233 11951 8337 9490 6728 4860 6222 560 11951 3084 740 11951 12708 797 7811 5994 7555 13328 560 9010 432 14330 11951 1178 </step>
    <step num="3">9179 11951 1319 13817 1397 13817 6142 560 2965 7317 </step>
    <step num="4">12785 11951 8337 560 5994 14361 12854 5895 2018 12854 7321 1391 5994 2597 3508 13823 </step>
    <step num="5">12474 5994 8372 10765 11020 6944 10662 1137 3988 371 9453 4080 210 11951 7668 1681 12091 6285 5527 12689 </step>
    <step num="6">7559 772 11951 1197 10950 5994 2597 14511 4120 11951 6885 6145 9889 308 13817 13033 4496 283 1681 6873 13817 8960 2257 5292 </step>
    <step num="7">8889 11951 5766 210 5994 2597 10083 1681 3557 13751 12738 1610 </step>
    <step num="8">12775 740 11951 12817 560 11951 6222 14158 8916 6285 13086 7811 5994 1441 7990 12002 11004 9309 2571 1681 10963 2147 12450 1940 12817 5376 5410 9741 6242 12339 6665 1939 12571 12785 11951 1940 12817 560 5994 12195 6880 817 11770 5994 10765 8800 </step>
    <step num="9">4829 8161 13981 10852 797 11801 371 11951 12817 210 11951 1388 4278 560 11951 12195 6880 13817 2234 1198 1046 560 2900 11353 13494 1391 1504 </step>
    <step num="10">9092 </step>
  </steps>
  <steps_updated>
    <steps_updated num="0">10950 5994 2597 10083 11770 13757 14307 4120 11951 10907 13384 9889 6145 13817 12051 </steps_updated>
    <steps_updated num="1">283 1681 11951 9924 9490 5335 13817 11951 2373 9490 11898 6285 2933 12689 </steps_updated>
    <steps_updated num="2">3783 8341 11951 13521 13817 3305 2168 1949 13817 11951 10765 11703 669 11951 6222 5802 10665 </steps_updated>
    <steps_updated num="3">8697 10279 13328 5465 7990 2933 3954 12689 </steps_updated>
    <steps_updated num="4">6054 11951 10083 6781 7855 13817 6142 1391 5994 7700 560 10694 11951 9453 </steps_updated>
    <steps_updated num="5">11233 11951 8337 9490 6728 4860 6222 560 11951 3084 740 11951 12708 797 7811 5994 7555 13328 560 9010 432 14330 11951 1178 </steps_updated>
    <steps_updated num="6">9179 11951 1319 13817 1397 13817 6142 560 2965 7317 </steps_updated>
    <steps_updated num="7">12785 11951 8337 560 5994 14361 12854 5895 2018 12854 7321 1391 5994 2597 3508 13823 </steps_updated>
    <steps_updated num="8">12474 5994 8372 10765 11020 6944 10662 1137 3988 371 9453 </steps_updated>
    <steps_updated num="9">4080 210 11951 7668 1681 12091 6285 5527 12689 </steps_updated>
    <steps_updated num="10">7559 772 11951 1197 10950 5994 2597 14511 4120 11951 6885 6145 9889 308 13817 13033 4496 </steps_updated>
    <steps_updated num="11">283 1681 6873 13817 8960 </steps_updated>
    <steps_updated num="12">2257 5292 </steps_updated>
    <steps_updated num="13">8889 11951 5766 210 5994 2597 10083 1681 3557 13751 12738 1610 </steps_updated>
    <steps_updated num="14">12775 740 11951 12817 560 11951 6222 14158 </steps_updated>
    <steps_updated num="15">8916 6285 13086 7811 5994 1441 7990 12002 11004 9309 2571 1681 10963 2147 </steps_updated>
    <steps_updated num="16">12450 1940 12817 5376 5410 9741 6242 12339 6665 1939 12571 </steps_updated>
    <steps_updated num="17">12785 11951 1940 12817 560 5994 12195 6880 817 11770 5994 10765 8800 </steps_updated>
    <steps_updated num="18">4829 8161 13981 10852 797 11801 371 11951 12817 210 11951 1388 </steps_updated>
    <steps_updated num="19">4278 560 11951 12195 6880 13817 2234 1198 1046 560 2900 11353 </steps_updated>
    <steps_updated num="20">13494 1391 1504 </steps_updated>
    <steps_updated num="21">9092 </steps_updated>
  </steps_updated>
</recipe>